pg_fdw/__init__.py
pg_fdw/admin.py
pg_fdw/app.py
pg_fdw/config.py
pg_fdw/connection.py
pg_fdw/main.py
pg_fdw/adapter/__init__.py
pg_fdw/adapter/adapter.py
pg_fdw/adapter/mysql.py
pg_fdw/adapter/oracle.py
pg_fdw/adapter/postgres.py
pg_fdw/config/config.yaml
pg_fdw/config/default.yaml
pg_fdw/config/schema.yaml
pg_fdw/fdw/__init__.py
pg_fdw/fdw/extension.py
pg_fdw/fdw/schema.py
pg_fdw/fdw/server.py
pg_fdw/fdw/user.py
pg_fdw/fdw/util.py
pg_fdw-0.0.9.dist-info/LICENSE
pg_fdw-0.0.9.dist-info/METADATA
pg_fdw-0.0.9.dist-info/WHEEL
pg_fdw-0.0.9.dist-info/entry_points.txt
pg_fdw-0.0.9.dist-info/top_level.txt
pg_fdw-0.0.9.dist-info/RECORD
