Metadata-Version: 2.1
Name: pg-fdw
Version: 0.0.9
Summary: Manage FDW extensions within Postgres
Author-email: Chumaky IT <info@chumaky.team>
License: MIT License
Project-URL: Homepage, https://github.com/chumaky/pg_fdw
Project-URL: Postgres HSQL FDW image, https://github.com/AmebaBrain/postgres_docker_images
Keywords: postgres,fdw,hsql
Classifier: Programming Language :: Python :: 3
Classifier: License :: OSI Approved :: MIT License
Classifier: Operating System :: OS Independent
Requires-Python: >=3.7
License-File: LICENSE
Requires-Dist: psycopg2
Requires-Dist: ruamel.yaml
